clip/__init__.py
clip/bpe_simple_vocab_16e6.txt.gz
clip/clip.py
clip/model.py
clip/simple_tokenizer.py
forager/__init__.py
forager/app.py
forager/buildutils.py
forager/main.py
forager_backend/__init__.py
forager_backend/asgi.py
forager_backend/settings.py
forager_backend/urls.py
forager_backend/wsgi.py
forager_backend_api/__init__.py
forager_backend_api/admin.py
forager_backend_api/apps.py
forager_backend_api/models.py
forager_backend_api/signals.py
forager_backend_api/tests.py
forager_backend_api/views.py
forager_backend_api/migrations/__init__.py
forager_embedding_server/__init__.py
forager_embedding_server/ais.py
forager_embedding_server/app.py
forager_embedding_server/bgsplit_jobs.py
forager_embedding_server/config.py
forager_embedding_server/embedding_jobs.py
forager_embedding_server/jobs_data.py
forager_embedding_server/log.py
forager_embedding_server/models.py
forager_embedding_server/utils.py
forager_frontend/__init__.py
forager_frontend/app.py
forager_frontend/log.py
forager_frontend/setup.py
forager_frontend/build/asset-manifest.json
forager_frontend/build/favicon.ico
forager_frontend/build/index.html
forager_frontend/build/logo192.png
forager_frontend/build/logo512.png
forager_frontend/build/manifest.json
forager_frontend/build/robots.txt
forager_frontend/build/assets/arrow-caret.svg
forager_frontend/build/static/css/2.426644c3.chunk.css
forager_frontend/build/static/css/2.426644c3.chunk.css.map
forager_frontend/build/static/css/main.adac7875.chunk.css
forager_frontend/build/static/css/main.adac7875.chunk.css.map
forager_frontend/build/static/js/2.bc23674f.chunk.js
forager_frontend/build/static/js/2.bc23674f.chunk.js.LICENSE.txt
forager_frontend/build/static/js/2.bc23674f.chunk.js.map
forager_frontend/build/static/js/main.13fa00fe.chunk.js
forager_frontend/build/static/js/main.13fa00fe.chunk.js.map
forager_frontend/build/static/js/runtime-main.ccc4a72d.js
forager_frontend/build/static/js/runtime-main.ccc4a72d.js.map
forager_knn/__init__.py
forager_server-0.0.2.post6.dist-info/METADATA
forager_server-0.0.2.post6.dist-info/WHEEL
forager_server-0.0.2.post6.dist-info/entry_points.txt
forager_server-0.0.2.post6.dist-info/top_level.txt
forager_server-0.0.2.post6.dist-info/RECORD
